frontivice/__init__.py
frontivice/main.py
frontivice-0.1.dist-info/METADATA
frontivice-0.1.dist-info/WHEEL
frontivice-0.1.dist-info/top_level.txt
frontivice-0.1.dist-info/RECORD
