Metadata-Version: 2.1
Name: frontivice
Version: 0.1
Summary: This package is designed to generate regular expression formats based on device names.
Author: Aung Htoo Khine
Requires-Dist: pydantic >=2.8.2
